odtmaker/contentParser.py
odtmaker-0.0.1.dist-info/LICENSE
odtmaker-0.0.1.dist-info/METADATA
odtmaker-0.0.1.dist-info/WHEEL
odtmaker-0.0.1.dist-info/entry_points.txt
odtmaker-0.0.1.dist-info/top_level.txt
odtmaker-0.0.1.dist-info/RECORD
