Metadata-Version: 2.1
Name: odtmaker
Version: 0.0.1
Summary: Small ODT generator
Home-page: https://bitbucket.org/rmonico/odtmaker
Author: Rafael Monico
Author-email: rmonico1@gmail.com
License: GPL3
License-File: LICENSE
Requires-Dist: ipdb
